bin/WTHMDA_example.py
bin/__init__.py
bin/get_disease_feature.py
bin/get_edges.py
bin/get_microbe_feature.py
example/WTHMDA_example.py
example/__init__.py
example/get_disease_feature.py
example/get_edges.py
example/get_microbe_feature.py
model/GCN_Model_weighted_8e.py
model/GraphConv.py
model/Weight_HeteroGraphConv.py
model/__init__.py
model/run_f_weighted.py
preproccess/__init__.py
preproccess/get_disease_feature_d.py
preproccess/get_disease_feature_h.py
preproccess/get_edges_d.py
preproccess/get_edges_h.py
preproccess/get_microbe_feature_d.py
preproccess/get_microbe_feature_h.py
run/WTHMDA_d.py
run/WTHMDA_h.py
run/__init__.py
utility/__init__.py
utility/dataset_weighted_8e.py
utility/evaluation2.py
WTHMDA-0.0.4.dist-info/METADATA
WTHMDA-0.0.4.dist-info/WHEEL
WTHMDA-0.0.4.dist-info/top_level.txt
WTHMDA-0.0.4.dist-info/RECORD
