Metadata-Version: 2.1
Name: WTHMDA
Version: 0.0.4
Summary: WTHMDA
Home-page: https://github.com/qdu-bioinfo/WTHMDA
Author: qdu-bioinfo
Author-email: suxq@qdu.edu.cn
License: UNKNOWN
Platform: UNKNOWN
Classifier: Programming Language :: Python :: 3
Classifier: License :: OSI Approved :: MIT License
Classifier: Operating System :: OS Independent
Requires-Python: >=3.6
